Metadata-Version: 2.1
Name: pymailclient
Version: 1.0.1
Summary: A Python Library to send email with template and and attachment via email
Home-page: https://github.com/finedevsam/pymail.git
Author: Samson Ilemobayo
Author-email: ilemobayosamson@gmail.com
License: UNKNOWN
Platform: UNKNOWN
Classifier: Programming Language :: Python :: 3
Classifier: License :: OSI Approved :: MIT License
Classifier: Operating System :: OS Independent
Requires-Python: >=3.6
License-File: LICENSE
